snowflakeapi/__init__.py
snowflakeapi/snowflakeapi.py
snowflakeapi-2.2.dist-info/LICENSE
snowflakeapi-2.2.dist-info/WHEEL
snowflakeapi-2.2.dist-info/METADATA
snowflakeapi-2.2.dist-info/RECORD
